{
  "kraken":
  {
    "model_prefix": "output",
    "nepoch": "epochs",
    "continue_from": "load",
    "learning_rate" : "lrate",
    "early_stop": "quit",
    "early_stop_min_improve": "min-delta",
    "early_stop_nbest": "lag",
    "device": "device",
    "weight_decay": "weight-decay"
  },
  "ocropus":
  {
    "model_prefix": "output",
    "nepoch": "ntrain",
    "learning_rate": "lrate",
    "continue_from": "load"
  },
  "calamari":
  {
    "model_prefix": "output_model_prefix",
    "nepoch": "max_iters",
    "continue_from": "weights",
    "early_stop_freq": "early_stopping_frequency",
    "early_stop_nbest": "early_stopping_nbest",
    "early_stop_model_prefix": "early_stopping_best_model_prefix",
    "savefreq": "checkpoint_frequency",
    "preload_train": "train_data_on_the_fly",
    "preload_test": "validation_data_on_the_fly",
    "num_threads_all": "num_threads",
    "num_threads_inter": "num_inter_threads",
    "num_threads_intra": "num_intra_threads"
  },
  "tesseract":
  {
    "model_prefix": "model_output",
    "nepoch": "max_iterations",
    "append": "append_index"
  }
}